gauge.py
circuitpython_gauge-0.3.0.dist-info/LICENSE
circuitpython_gauge-0.3.0.dist-info/METADATA
circuitpython_gauge-0.3.0.dist-info/WHEEL
circuitpython_gauge-0.3.0.dist-info/top_level.txt
circuitpython_gauge-0.3.0.dist-info/RECORD
