Metadata-Version: 2.1
Name: circuitpython-gauge
Version: 0.3.0
Summary: CircuitPython Gauge
Author-email: "Jose D. Montoya" <gauge@mailmeto.mozmail.com>
License: MIT
Project-URL: Homepage, https://github.com/jposada202020/CircuitPython_Gauge
Keywords: adafruit,blinka,circuitpython,micropython,gauge,gauge,plot,graphial,gage,uplot,meter
Classifier: Intended Audience :: Developers
Classifier: Topic :: Software Development :: Libraries
Classifier: Topic :: Software Development :: Embedded Systems
Classifier: Topic :: System :: Hardware
Classifier: License :: OSI Approved :: MIT License
Classifier: Programming Language :: Python :: 3
License-File: LICENSE
Requires-Dist: Adafruit-Blinka
Provides-Extra: optional
